gaiacone/VERSION
gaiacone/__init__.py
gaiacone/cone.py
GaiaCone-0.0.1.dist-info/LICENSE
GaiaCone-0.0.1.dist-info/METADATA
GaiaCone-0.0.1.dist-info/WHEEL
GaiaCone-0.0.1.dist-info/top_level.txt
GaiaCone-0.0.1.dist-info/RECORD
