Metadata-Version: 2.1
Name: GaiaCone
Version: 0.0.1
Summary: A library for GaiaCone.
Author-email: Matt Lehnert <matthew.lehnert@axleinfo.com>
Maintainer-email: Matt Lehnert <matthew.lehnert@axleinfo.com>
License: MIT License
Project-URL: Documentation, https://gaiacone.readthedocs.io/en/latest/
Project-URL: Repository, https://github.com/PolusAI/CONE
Classifier: Development Status :: 3 - Alpha
Classifier: Programming Language :: Python :: 3
Classifier: License :: OSI Approved :: MIT License
Classifier: Operating System :: OS Independent
Requires-Python: >=3.9
License-File: LICENSE
Requires-Dist: numpy
